Metadata-Version: 2.1
Name: argparse-ext
Version: 1.3.0
Summary: argparse ext;
Home-page: https://github.com/cykerway/argparse-ext
Author: Cyker Way
Author-email: cykerway@example.com
License: UNKNOWN
Project-URL: Bug Reports, https://github.com/cykerway/argparse-ext/issues
Project-URL: Source, https://github.com/cykerway/argparse-ext/
Keywords: argparse ext
Platform: UNKNOWN
Classifier: Development Status :: 3 - Alpha
Classifier: Intended Audience :: Developers
Classifier: Topic :: Desktop Environment
Classifier: License :: OSI Approved :: GNU General Public License v3 (GPLv3)
Classifier: Programming Language :: Python :: 3.6
Classifier: Programming Language :: Python :: 3.7
